nodens/update/__init__.py
nodens/update/__main__.py
nodens/update/nodens_fns.py
nodens/update/nodens_mesh.py
nodens/update/nodens_quick_serv.py
nodens_update-23.1.0.dist-info/LICENSE
nodens_update-23.1.0.dist-info/METADATA
nodens_update-23.1.0.dist-info/WHEEL
nodens_update-23.1.0.dist-info/entry_points.txt
nodens_update-23.1.0.dist-info/top_level.txt
nodens_update-23.1.0.dist-info/RECORD
