Metadata-Version: 2.1
Name: nodens-update
Version: 23.1.0
Summary: Update a NodeNs sensor connected to the gateway
Author-email: Khalid Z Rajab <khalid@nodens.eu>
License: The MIT License (MIT)
Project-URL: Homepage, https://www.nodens.eu
Keywords: nodens,gateway,radar
Classifier: License :: OSI Approved :: MIT License
Classifier: Programming Language :: Python
Classifier: Programming Language :: Python :: 3
Requires-Python: >=3.7
License-File: LICENSE
Requires-Dist: paho-mqtt
Requires-Dist: pyyaml
Requires-Dist: numpy
Requires-Dist: platformdirs
Requires-Dist: tomli ; python_version < "3.11"
